tracia/__init__.py
tracia-0.0.1.dist-info/METADATA
tracia-0.0.1.dist-info/WHEEL
tracia-0.0.1.dist-info/licenses/LICENSE
tracia-0.0.1.dist-info/RECORD
